{
"type": "FeatureCollection",
"name": "point",
"crs": { "type": "name", "properties": { "name": "urn:ogc:def:crs:EPSG::6667" } },
"features": [
{ "type": "Feature", "properties": { "CONAME": "MO186", "COY": "-15617.986", "COX": "-13737.237", "CONOTE1": "コンクリート杭", "CONOTE2": null }, "geometry": { "type": "Point", "coordinates": [ 139.660368199585662, 35.876057196007132 ] } },
{ "type": "Feature", "properties": { "CONAME": "MO179", "COY": "-15620.136", "COX": "-13724.501", "CONOTE1": "金属鋲", "CONOTE2": null }, "geometry": { "type": "Point", "coordinates": [ 139.660344139425916, 35.876171956184599 ] } },
{ "type": "Feature", "properties": { "CONAME": "MO178", "COY": "-15620.495", "COX": "-13724.526", "CONOTE1": "コンクリート杭", "CONOTE2": null }, "geometry": { "type": "Point", "coordinates": [ 139.660340164094691, 35.87617172512455 ] } },
{ "type": "Feature", "properties": { "CONAME": "MO181", "COY": "-15622.154", "COX": "-13713.301", "CONOTE1": "コンクリート杭", "CONOTE2": null }, "geometry": { "type": "Point", "coordinates": [ 139.660321571162626, 35.876272873902295 ] } },
{ "type": "Feature", "properties": { "CONAME": "M8061", "COY": "-15623.756", "COX": "-13701.630", "CONOTE1": "コンクリート杭", "CONOTE2": null }, "geometry": { "type": "Point", "coordinates": [ 139.660303600701184, 35.876378043553821 ] } },
{ "type": "Feature", "properties": { "CONAME": "M8058", "COY": "-15625.205", "COX": "-13690.960", "CONOTE1": "計算点", "CONOTE2": null }, "geometry": { "type": "Point", "coordinates": [ 139.660287344250634, 35.876474193244412 ] } },
{ "type": "Feature", "properties": { "CONAME": "M0557", "COY": "-15621.391", "COX": "-13691.005", "CONOTE1": "コンクリート杭", "CONOTE2": null }, "geometry": { "type": "Point", "coordinates": [ 139.660329584239264, 35.87647384848124 ] } },
{ "type": "Feature", "properties": { "CONAME": "M0558", "COY": "-15618.899", "COX": "-13691.036", "CONOTE1": "コンクリート杭", "CONOTE2": null }, "geometry": { "type": "Point", "coordinates": [ 139.660357183130287, 35.876473608809526 ] } },
{ "type": "Feature", "properties": { "CONAME": "M8301", "COY": "-15616.941", "COX": "-13693.312", "CONOTE1": "計算点", "CONOTE2": null }, "geometry": { "type": "Point", "coordinates": [ 139.660378912086571, 35.876453125570158 ] } },
{ "type": "Feature", "properties": { "CONAME": "M8303", "COY": "-15615.806", "COX": "-13700.768", "CONOTE1": "計算点", "CONOTE2": null }, "geometry": { "type": "Point", "coordinates": [ 139.660391627992084, 35.876385939876442 ] } },
{ "type": "Feature", "properties": { "CONAME": "M8304", "COY": "-15615.238", "COX": "-13704.603", "CONOTE1": "計算点", "CONOTE2": null }, "geometry": { "type": "Point", "coordinates": [ 139.660397993570143, 35.876351382604646 ] } },
{ "type": "Feature", "properties": { "CONAME": "M8308", "COY": "-15613.515", "COX": "-13715.862", "CONOTE1": "計算点", "CONOTE2": null }, "geometry": { "type": "Point", "coordinates": [ 139.660417295872037, 35.87624992838137 ] } },
{ "type": "Feature", "properties": { "CONAME": "M8339", "COY": "-15612.469", "COX": "-13723.088", "CONOTE1": "計算点", "CONOTE2": null }, "geometry": { "type": "Point", "coordinates": [ 139.660429021557889, 35.876184814340853 ] } },
{ "type": "Feature", "properties": { "CONAME": "M8340", "COY": "-15612.386", "COX": "-13723.656", "CONOTE1": "計算点", "CONOTE2": null }, "geometry": { "type": "Point", "coordinates": [ 139.660429951883685, 35.876179696061605 ] } },
{ "type": "Feature", "properties": { "CONAME": "M8337", "COY": "-15612.268", "COX": "-13724.473", "CONOTE1": "計算点", "CONOTE2": null }, "geometry": { "type": "Point", "coordinates": [ 139.66043127470104, 35.876172334007542 ] } },
{ "type": "Feature", "properties": { "CONAME": "M8336", "COY": "-15611.284", "COX": "-13731.157", "CONOTE1": "計算点", "CONOTE2": null }, "geometry": { "type": "Point", "coordinates": [ 139.660442303117577, 35.876112104230899 ] } },
{ "type": "Feature", "properties": { "CONAME": "M0526", "COY": "-15610.726", "COX": "-13734.044", "CONOTE1": "計算点", "CONOTE2": null }, "geometry": { "type": "Point", "coordinates": [ 139.660448539339114, 35.876086091483813 ] } },
{ "type": "Feature", "properties": { "CONAME": "M8349", "COY": "-15612.677", "COX": "-13736.324", "CONOTE1": "コンクリート杭", "CONOTE2": null }, "geometry": { "type": "Point", "coordinates": [ 139.660426977257856, 35.876065509869335 ] } }
]
}
